warped/__init__.py
warped/actions.py
warped/argparser_wrapper.py
warped/context.py
warped/hook.py
warped/savemodules.py
warped/views.py
warped/samples/__init__.py
warped/samples/hooked.py
warped/samples/subparsertest.py
warped/samples/test.py
warped/static/css/.app.css.swp
warped/static/css/app.css
warped/static/css/foundation.css
warped/static/css/foundation.min.css
warped/static/icons/.DS_Store
warped/static/icons/.fontcustom-data
warped/static/icons/foundation-icons.css
warped/static/icons/foundation-icons.eot
warped/static/icons/foundation-icons.svg
warped/static/icons/foundation-icons.ttf
warped/static/icons/foundation-icons.woff
warped/static/icons/preview.html
warped/static/icons/svgs/fi-address-book.svg
warped/static/icons/svgs/fi-alert.svg
warped/static/icons/svgs/fi-align-center.svg
warped/static/icons/svgs/fi-align-justify.svg
warped/static/icons/svgs/fi-align-left.svg
warped/static/icons/svgs/fi-align-right.svg
warped/static/icons/svgs/fi-anchor.svg
warped/static/icons/svgs/fi-annotate.svg
warped/static/icons/svgs/fi-archive.svg
warped/static/icons/svgs/fi-arrow-down.svg
warped/static/icons/svgs/fi-arrow-left.svg
warped/static/icons/svgs/fi-arrow-right.svg
warped/static/icons/svgs/fi-arrow-up.svg
warped/static/icons/svgs/fi-arrows-compress.svg
warped/static/icons/svgs/fi-arrows-expand.svg
warped/static/icons/svgs/fi-arrows-in.svg
warped/static/icons/svgs/fi-arrows-out.svg
warped/static/icons/svgs/fi-asl.svg
warped/static/icons/svgs/fi-asterisk.svg
warped/static/icons/svgs/fi-at-sign.svg
warped/static/icons/svgs/fi-background-color.svg
warped/static/icons/svgs/fi-battery-empty.svg
warped/static/icons/svgs/fi-battery-full.svg
warped/static/icons/svgs/fi-battery-half.svg
warped/static/icons/svgs/fi-bitcoin-circle.svg
warped/static/icons/svgs/fi-bitcoin.svg
warped/static/icons/svgs/fi-blind.svg
warped/static/icons/svgs/fi-bluetooth.svg
warped/static/icons/svgs/fi-bold.svg
warped-0.1.3.dist-info/DESCRIPTION.rst
warped-0.1.3.dist-info/METADATA
warped-0.1.3.dist-info/RECORD
warped-0.1.3.dist-info/WHEEL
warped-0.1.3.dist-info/entry_points.txt
warped-0.1.3.dist-info/metadata.json
warped-0.1.3.dist-info/top_level.txt
