Metadata-Version: 2.0
Name: warped
Version: 0.1.3
Summary: A webbased wrapper for the argument parser in Python
Home-page: https://git.k-fortytwo.de/christofsteel/warp
Author: Christoph Stahl
Author-email: christoph.stahl@uni-dortmund.de
License: MIT
Download-URL: https://git.k-fortytwo.de/christofsteel/warped/archive/0.1.3.tar.gz
Platform: UNKNOWN
Requires-Dist: Flask
